GracefulKiller/GracefulKiller.py
GracefulKiller/__init__.py
GracefulKiller-0.4.7.dist-info/LICENSE
GracefulKiller-0.4.7.dist-info/METADATA
GracefulKiller-0.4.7.dist-info/WHEEL
GracefulKiller-0.4.7.dist-info/top_level.txt
GracefulKiller-0.4.7.dist-info/RECORD
