Metadata-Version: 2.1
Name: GracefulKiller
Version: 0.4.7
Summary: module for process SIGTERM, SIGHUP and SIGINT signals gracefully
Home-page: https://github.com/MaxMaxoff/GracefulKiller
Download-URL: https://github.com/MaxMaxoff/GracefulKiller/archive/v0.4.7.tar.gz
Author: Maxim Toropov
Author-email: maxim.vt@gmail.com
License: MIT
Keywords: SIGTERM,SIGINT,SIGHUP,GracefulKiller,Killer,Graceful
Classifier: Development Status :: 5 - Production/Stable
Classifier: Intended Audience :: Developers
Classifier: Topic :: Software Development :: Build Tools
Classifier: License :: OSI Approved :: MIT License
Classifier: Programming Language :: Python :: 3
Classifier: Programming Language :: Python :: 3.6
Classifier: Programming Language :: Python :: 3.7
Classifier: Programming Language :: Python :: 3.8
Classifier: Programming Language :: Python :: 3.9
Classifier: Programming Language :: Python :: 3.10
Classifier: Programming Language :: Python :: 3.11
Classifier: Programming Language :: Python :: 3.12
Classifier: Programming Language :: Python :: 3.13
Requires-Python: >=3.6
License-File: LICENSE
